plnlp/__init__.py
plnlp/__main__.py
plnlp/defs.py
plnlp/utils.py
plnlp-1.0.1.dist-info/METADATA
plnlp-1.0.1.dist-info/WHEEL
plnlp-1.0.1.dist-info/entry_points.txt
plnlp-1.0.1.dist-info/top_level.txt
plnlp-1.0.1.dist-info/RECORD
